{
  "updated_at": "2026-05-17T13:21:37.989651+00:00",
  "airport_icao": "SBFI",
  "airport_name": "Foz do Iguacu",
  "source": "AviationStack",
  "arrivals": [
    {
      "callsign": "TP5992",
      "airline": "TAP Air Portugal",
      "airport": "SBGL",
      "airport_name": "Rio de Janeiro / Galeao",
      "scheduled": "2026-05-17T15:55:00+00:00",
      "time_iso": "2026-05-17T15:55:00+00:00",
      "status": "programado"
    },
    {
      "callsign": "AD3059",
      "airline": "Azul",
      "airport": "SBGL",
      "airport_name": "Rio de Janeiro / Galeao",
      "scheduled": "2026-05-17T15:55:00+00:00",
      "time_iso": "2026-05-17T15:55:00+00:00",
      "status": "programado"
    },
    {
      "callsign": "LA3481",
      "airline": "LATAM Airlines",
      "airport": "SBCT",
      "airport_name": "Curitiba",
      "scheduled": "2026-05-17T16:40:00+00:00",
      "time_iso": "2026-05-17T16:40:00+00:00",
      "status": "programado"
    },
    {
      "callsign": "LA3290",
      "airline": "LATAM Airlines",
      "airport": "SBGL",
      "airport_name": "Rio de Janeiro / Galeao",
      "scheduled": "2026-05-17T16:30:00+00:00",
      "time_iso": "2026-05-17T16:30:00+00:00",
      "status": "programado"
    },
    {
      "callsign": "CA7129",
      "airline": "Air China",
      "airport": "SBGR",
      "airport_name": "Sao Paulo / Guarulhos",
      "scheduled": "2026-05-17T14:05:00+00:00",
      "time_iso": "2026-05-17T14:05:00+00:00",
      "status": "programado"
    },
    {
      "callsign": "TP6265",
      "airline": "TAP Air Portugal",
      "airport": "SBGR",
      "airport_name": "Sao Paulo / Guarulhos",
      "scheduled": "2026-05-17T14:05:00+00:00",
      "time_iso": "2026-05-17T14:05:00+00:00",
      "status": "programado"
    },
    {
      "callsign": "QR7263",
      "airline": "Qatar Airways",
      "airport": "SBGR",
      "airport_name": "Sao Paulo / Guarulhos",
      "scheduled": "2026-05-17T14:05:00+00:00",
      "time_iso": "2026-05-17T14:05:00+00:00",
      "status": "programado"
    },
    {
      "callsign": "IB6604",
      "airline": "Iberia",
      "airport": "SBGR",
      "airport_name": "Sao Paulo / Guarulhos",
      "scheduled": "2026-05-17T14:05:00+00:00",
      "time_iso": "2026-05-17T14:05:00+00:00",
      "status": "programado"
    },
    {
      "callsign": "DL6269",
      "airline": "Delta Air Lines",
      "airport": "SBGR",
      "airport_name": "Sao Paulo / Guarulhos",
      "scheduled": "2026-05-17T14:05:00+00:00",
      "time_iso": "2026-05-17T14:05:00+00:00",
      "status": "programado"
    },
    {
      "callsign": "BA7655",
      "airline": "British Airways",
      "airport": "SBGR",
      "airport_name": "Sao Paulo / Guarulhos",
      "scheduled": "2026-05-17T14:05:00+00:00",
      "time_iso": "2026-05-17T14:05:00+00:00",
      "status": "programado"
    },
    {
      "callsign": "AM8526",
      "airline": "Aeromexico",
      "airport": "SBGR",
      "airport_name": "Sao Paulo / Guarulhos",
      "scheduled": "2026-05-17T14:05:00+00:00",
      "time_iso": "2026-05-17T14:05:00+00:00",
      "status": "programado"
    },
    {
      "callsign": "EK3687",
      "airline": "Emirates",
      "airport": "SBGL",
      "airport_name": "Rio de Janeiro / Galeao",
      "scheduled": "2026-05-17T14:05:00+00:00",
      "time_iso": "2026-05-17T14:05:00+00:00",
      "status": "programado"
    },
    {
      "callsign": "AV2671",
      "airline": "avianca",
      "airport": "SBGL",
      "airport_name": "Rio de Janeiro / Galeao",
      "scheduled": "2026-05-17T14:05:00+00:00",
      "time_iso": "2026-05-17T14:05:00+00:00",
      "status": "programado"
    },
    {
      "callsign": "AD3004",
      "airline": "Azul",
      "airport": "SBGL",
      "airport_name": "Rio de Janeiro / Galeao",
      "scheduled": "2026-05-17T14:05:00+00:00",
      "time_iso": "2026-05-17T14:05:00+00:00",
      "status": "programado"
    },
    {
      "callsign": "TP5766",
      "airline": "TAP Air Portugal",
      "airport": "SBGL",
      "airport_name": "Rio de Janeiro / Galeao",
      "scheduled": "2026-05-17T14:05:00+00:00",
      "time_iso": "2026-05-17T14:05:00+00:00",
      "status": "programado"
    },
    {
      "callsign": "AV2647",
      "airline": "avianca",
      "airport": "SBGL",
      "airport_name": "Rio de Janeiro / Galeao",
      "scheduled": "2026-05-17T14:05:00+00:00",
      "time_iso": "2026-05-17T14:05:00+00:00",
      "status": "programado"
    },
    {
      "callsign": "AD3132",
      "airline": "Azul",
      "airport": "SBGL",
      "airport_name": "Rio de Janeiro / Galeao",
      "scheduled": "2026-05-17T14:05:00+00:00",
      "time_iso": "2026-05-17T14:05:00+00:00",
      "status": "programado"
    },
    {
      "callsign": "AA7709",
      "airline": "American Airlines",
      "airport": "SBGL",
      "airport_name": "Rio de Janeiro / Galeao",
      "scheduled": "2026-05-17T14:05:00+00:00",
      "time_iso": "2026-05-17T14:05:00+00:00",
      "status": "programado"
    },
    {
      "callsign": "G31390",
      "airline": "GOL",
      "airport": "SBGL",
      "airport_name": "Rio de Janeiro / Galeao",
      "scheduled": "2026-05-17T15:55:00+00:00",
      "time_iso": "2026-05-17T15:55:00+00:00",
      "status": "programado"
    },
    {
      "callsign": "AD2955",
      "airline": "Azul",
      "airport": "SBKP",
      "airport_name": "Campinas / Viracopos",
      "scheduled": "2026-05-17T14:40:00+00:00",
      "time_iso": "2026-05-17T14:40:00+00:00",
      "status": "programado"
    },
    {
      "callsign": "LA3202",
      "airline": "LATAM Airlines",
      "airport": "SBGR",
      "airport_name": "Sao Paulo / Guarulhos",
      "scheduled": "2026-05-17T14:05:00+00:00",
      "time_iso": "2026-05-17T14:05:00+00:00",
      "status": "programado"
    },
    {
      "callsign": "G31944",
      "airline": "GOL",
      "airport": "SBGL",
      "airport_name": "Rio de Janeiro / Galeao",
      "scheduled": "2026-05-17T14:05:00+00:00",
      "time_iso": "2026-05-17T14:05:00+00:00",
      "status": "programado"
    },
    {
      "callsign": "G31122",
      "airline": "GOL",
      "airport": "SBSP",
      "airport_name": "Sao Paulo / Congonhas",
      "scheduled": "2026-05-17T13:35:00+00:00",
      "time_iso": "2026-05-17T13:35:00+00:00",
      "status": "programado"
    },
    {
      "callsign": "AD6002",
      "airline": "Azul",
      "airport": "SBSP",
      "airport_name": "Sao Paulo / Congonhas",
      "scheduled": "2026-05-17T13:15:00+00:00",
      "time_iso": "2026-05-17T13:15:00+00:00",
      "status": "programado"
    },
    {
      "callsign": "LA4520",
      "airline": "LATAM Airlines",
      "airport": "SBSP",
      "airport_name": "Sao Paulo / Congonhas",
      "scheduled": "2026-05-17T12:55:00+00:00",
      "time_iso": "2026-05-17T12:55:00+00:00",
      "status": "programado"
    },
    {
      "callsign": "TK9421",
      "airline": "Turkish Airlines",
      "airport": "SBGR",
      "airport_name": "Sao Paulo / Guarulhos",
      "scheduled": "2026-05-17T10:35:00+00:00",
      "time_iso": "2026-05-17T10:43:00+00:00",
      "status": "em voo"
    },
    {
      "callsign": "UX2625",
      "airline": "Air Europa",
      "airport": "SBGR",
      "airport_name": "Sao Paulo / Guarulhos",
      "scheduled": "2026-05-17T10:35:00+00:00",
      "time_iso": "2026-05-17T10:43:00+00:00",
      "status": "em voo"
    },
    {
      "callsign": "TP4072",
      "airline": "TAP Air Portugal",
      "airport": "SBGR",
      "airport_name": "Sao Paulo / Guarulhos",
      "scheduled": "2026-05-17T10:35:00+00:00",
      "time_iso": "2026-05-17T10:43:00+00:00",
      "status": "em voo"
    },
    {
      "callsign": "TK8415",
      "airline": "Turkish Airlines",
      "airport": "SBGR",
      "airport_name": "Sao Paulo / Guarulhos",
      "scheduled": "2026-05-17T10:35:00+00:00",
      "time_iso": "2026-05-17T10:43:00+00:00",
      "status": "em voo"
    },
    {
      "callsign": "KL9320",
      "airline": "KLM",
      "airport": "SBGR",
      "airport_name": "Sao Paulo / Guarulhos",
      "scheduled": "2026-05-17T10:35:00+00:00",
      "time_iso": "2026-05-17T10:43:00+00:00",
      "status": "em voo"
    },
    {
      "callsign": "ET4170",
      "airline": "Ethiopian Airlines",
      "airport": "SBGR",
      "airport_name": "Sao Paulo / Guarulhos",
      "scheduled": "2026-05-17T10:35:00+00:00",
      "time_iso": "2026-05-17T10:43:00+00:00",
      "status": "em voo"
    },
    {
      "callsign": "EK3627",
      "airline": "Emirates",
      "airport": "SBGR",
      "airport_name": "Sao Paulo / Guarulhos",
      "scheduled": "2026-05-17T10:35:00+00:00",
      "time_iso": "2026-05-17T10:43:00+00:00",
      "status": "em voo"
    },
    {
      "callsign": "CM3579",
      "airline": "Copa Airlines",
      "airport": "SBGR",
      "airport_name": "Sao Paulo / Guarulhos",
      "scheduled": "2026-05-17T10:35:00+00:00",
      "time_iso": "2026-05-17T10:43:00+00:00",
      "status": "em voo"
    },
    {
      "callsign": "AV4658",
      "airline": "avianca",
      "airport": "SBGR",
      "airport_name": "Sao Paulo / Guarulhos",
      "scheduled": "2026-05-17T10:35:00+00:00",
      "time_iso": "2026-05-17T10:43:00+00:00",
      "status": "em voo"
    },
    {
      "callsign": "AT9074",
      "airline": "Royal Air Maroc",
      "airport": "SBGR",
      "airport_name": "Sao Paulo / Guarulhos",
      "scheduled": "2026-05-17T10:35:00+00:00",
      "time_iso": "2026-05-17T10:43:00+00:00",
      "status": "em voo"
    },
    {
      "callsign": "AF1931",
      "airline": "Air France",
      "airport": "SBGR",
      "airport_name": "Sao Paulo / Guarulhos",
      "scheduled": "2026-05-17T10:35:00+00:00",
      "time_iso": "2026-05-17T10:43:00+00:00",
      "status": "em voo"
    },
    {
      "callsign": "AA7724",
      "airline": "American Airlines",
      "airport": "SBGR",
      "airport_name": "Sao Paulo / Guarulhos",
      "scheduled": "2026-05-17T10:35:00+00:00",
      "time_iso": "2026-05-17T10:43:00+00:00",
      "status": "em voo"
    },
    {
      "callsign": "AD4233",
      "airline": "Azul",
      "airport": "SBCT",
      "airport_name": "Curitiba",
      "scheduled": "2026-05-17T12:05:00+00:00",
      "time_iso": "2026-05-17T12:05:00+00:00",
      "status": "programado"
    },
    {
      "callsign": "CA7121",
      "airline": "Air China",
      "airport": "SBGR",
      "airport_name": "Sao Paulo / Guarulhos",
      "scheduled": "2026-05-17T09:20:00+00:00",
      "time_iso": "2026-05-17T09:37:00+00:00",
      "status": "pousado"
    },
    {
      "callsign": "TK9555",
      "airline": "Turkish Airlines",
      "airport": "SBGR",
      "airport_name": "Sao Paulo / Guarulhos",
      "scheduled": "2026-05-17T09:20:00+00:00",
      "time_iso": "2026-05-17T09:37:00+00:00",
      "status": "pousado"
    },
    {
      "callsign": "QR8414",
      "airline": "Qatar Airways",
      "airport": "SBGR",
      "airport_name": "Sao Paulo / Guarulhos",
      "scheduled": "2026-05-17T09:20:00+00:00",
      "time_iso": "2026-05-17T09:37:00+00:00",
      "status": "pousado"
    },
    {
      "callsign": "LX9716",
      "airline": "Swiss",
      "airport": "SBGR",
      "airport_name": "Sao Paulo / Guarulhos",
      "scheduled": "2026-05-17T09:20:00+00:00",
      "time_iso": "2026-05-17T09:37:00+00:00",
      "status": "pousado"
    },
    {
      "callsign": "LH4692",
      "airline": "Lufthansa",
      "airport": "SBGR",
      "airport_name": "Sao Paulo / Guarulhos",
      "scheduled": "2026-05-17T09:20:00+00:00",
      "time_iso": "2026-05-17T09:37:00+00:00",
      "status": "pousado"
    },
    {
      "callsign": "JL5548",
      "airline": "Japan Airlines",
      "airport": "SBGR",
      "airport_name": "Sao Paulo / Guarulhos",
      "scheduled": "2026-05-17T09:20:00+00:00",
      "time_iso": "2026-05-17T09:37:00+00:00",
      "status": "pousado"
    },
    {
      "callsign": "IB6492",
      "airline": "Iberia",
      "airport": "SBGR",
      "airport_name": "Sao Paulo / Guarulhos",
      "scheduled": "2026-05-17T09:20:00+00:00",
      "time_iso": "2026-05-17T09:37:00+00:00",
      "status": "pousado"
    },
    {
      "callsign": "DL6205",
      "airline": "Delta Air Lines",
      "airport": "SBGR",
      "airport_name": "Sao Paulo / Guarulhos",
      "scheduled": "2026-05-17T09:20:00+00:00",
      "time_iso": "2026-05-17T09:37:00+00:00",
      "status": "pousado"
    },
    {
      "callsign": "LA3460",
      "airline": "LATAM Airlines",
      "airport": "SBBR",
      "airport_name": "Brasilia",
      "scheduled": "2026-05-17T10:40:00+00:00",
      "time_iso": "2026-05-17T10:43:00+00:00",
      "status": "em voo"
    },
    {
      "callsign": "G31178",
      "airline": "GOL",
      "airport": "SBGR",
      "airport_name": "Sao Paulo / Guarulhos",
      "scheduled": "2026-05-17T10:35:00+00:00",
      "time_iso": "2026-05-17T10:43:00+00:00",
      "status": "em voo"
    },
    {
      "callsign": "LA3200",
      "airline": "LATAM Airlines",
      "airport": "SBGR",
      "airport_name": "Sao Paulo / Guarulhos",
      "scheduled": "2026-05-17T09:20:00+00:00",
      "time_iso": "2026-05-17T09:37:00+00:00",
      "status": "pousado"
    },
    {
      "callsign": "G31860",
      "airline": "GOL",
      "airport": "SBGL",
      "airport_name": "Rio de Janeiro / Galeao",
      "scheduled": "2026-05-17T09:30:00+00:00",
      "time_iso": "2026-05-17T09:30:00+00:00",
      "status": "pousado"
    },
    {
      "callsign": "TP4111",
      "airline": "TAP Air Portugal",
      "airport": "SBGL",
      "airport_name": "Rio de Janeiro / Galeao",
      "scheduled": "2026-05-17T09:30:00+00:00",
      "time_iso": "2026-05-17T09:30:00+00:00",
      "status": "pousado"
    },
    {
      "callsign": "KL9362",
      "airline": "KLM",
      "airport": "SBGL",
      "airport_name": "Rio de Janeiro / Galeao",
      "scheduled": "2026-05-17T09:30:00+00:00",
      "time_iso": "2026-05-17T09:30:00+00:00",
      "status": "pousado"
    },
    {
      "callsign": "EK3689",
      "airline": "Emirates",
      "airport": "SBGL",
      "airport_name": "Rio de Janeiro / Galeao",
      "scheduled": "2026-05-17T09:30:00+00:00",
      "time_iso": "2026-05-17T09:30:00+00:00",
      "status": "pousado"
    },
    {
      "callsign": "AD3061",
      "airline": "Azul",
      "airport": "SBGL",
      "airport_name": "Rio de Janeiro / Galeao",
      "scheduled": "2026-05-17T09:30:00+00:00",
      "time_iso": "2026-05-17T09:30:00+00:00",
      "status": "pousado"
    },
    {
      "callsign": "AD6074",
      "airline": "Azul",
      "airport": "SBSP",
      "airport_name": "Sao Paulo / Congonhas",
      "scheduled": "2026-05-17T08:15:00+00:00",
      "time_iso": "2026-05-17T08:11:00+00:00",
      "status": "pousado"
    },
    {
      "callsign": "JA786",
      "airline": "JetSMART",
      "airport": "SCEL",
      "airport_name": "SCEL",
      "scheduled": "2026-05-17T08:15:00+00:00",
      "time_iso": "2026-05-17T08:01:00+00:00",
      "status": "em voo"
    },
    {
      "callsign": "TP4126",
      "airline": "TAP Air Portugal",
      "airport": "SBGL",
      "airport_name": "Rio de Janeiro / Galeao",
      "scheduled": "2026-05-17T02:15:00+00:00",
      "time_iso": "2026-05-17T01:52:00+00:00",
      "status": "pousado"
    },
    {
      "callsign": "KL9452",
      "airline": "KLM",
      "airport": "SBGL",
      "airport_name": "Rio de Janeiro / Galeao",
      "scheduled": "2026-05-17T02:15:00+00:00",
      "time_iso": "2026-05-17T01:52:00+00:00",
      "status": "pousado"
    },
    {
      "callsign": "AF1972",
      "airline": "Air France",
      "airport": "SBGL",
      "airport_name": "Rio de Janeiro / Galeao",
      "scheduled": "2026-05-17T02:15:00+00:00",
      "time_iso": "2026-05-17T01:52:00+00:00",
      "status": "pousado"
    },
    {
      "callsign": "AD3065",
      "airline": "Azul",
      "airport": "SBGL",
      "airport_name": "Rio de Janeiro / Galeao",
      "scheduled": "2026-05-17T02:15:00+00:00",
      "time_iso": "2026-05-17T01:52:00+00:00",
      "status": "pousado"
    },
    {
      "callsign": "QR7297",
      "airline": "Qatar Airways",
      "airport": "SBGR",
      "airport_name": "Sao Paulo / Guarulhos",
      "scheduled": "2026-05-17T00:05:00+00:00",
      "time_iso": "2026-05-17T00:22:00+00:00",
      "status": "programado"
    },
    {
      "callsign": "DL6725",
      "airline": "Delta Air Lines",
      "airport": "SBGR",
      "airport_name": "Sao Paulo / Guarulhos",
      "scheduled": "2026-05-17T00:05:00+00:00",
      "time_iso": "2026-05-17T00:22:00+00:00",
      "status": "programado"
    },
    {
      "callsign": "G31868",
      "airline": "GOL",
      "airport": "SBGL",
      "airport_name": "Rio de Janeiro / Galeao",
      "scheduled": "2026-05-17T02:15:00+00:00",
      "time_iso": "2026-05-17T01:52:00+00:00",
      "status": "pousado"
    },
    {
      "callsign": "LA3206",
      "airline": "LATAM Airlines",
      "airport": "SBGR",
      "airport_name": "Sao Paulo / Guarulhos",
      "scheduled": "2026-05-17T00:05:00+00:00",
      "time_iso": "2026-05-17T00:22:00+00:00",
      "status": "programado"
    },
    {
      "callsign": "LA3220",
      "airline": "LATAM Airlines",
      "airport": "SBSP",
      "airport_name": "Sao Paulo / Congonhas",
      "scheduled": "2026-05-16T23:40:00+00:00",
      "time_iso": "2026-05-16T23:19:00+00:00",
      "status": "pousado"
    },
    {
      "callsign": "DT6172",
      "airline": "TAAG Angola Airlines",
      "airport": "SBGR",
      "airport_name": "Sao Paulo / Guarulhos",
      "scheduled": "2026-05-16T20:10:00+00:00",
      "time_iso": "2026-05-16T19:58:00+00:00",
      "status": "pousado"
    },
    {
      "callsign": "AM8050",
      "airline": "Aeromexico",
      "airport": "SBGR",
      "airport_name": "Sao Paulo / Guarulhos",
      "scheduled": "2026-05-16T20:10:00+00:00",
      "time_iso": "2026-05-16T19:58:00+00:00",
      "status": "pousado"
    },
    {
      "callsign": "UX2307",
      "airline": "Air Europa",
      "airport": "SBGR",
      "airport_name": "Sao Paulo / Guarulhos",
      "scheduled": "2026-05-16T20:10:00+00:00",
      "time_iso": "2026-05-16T19:58:00+00:00",
      "status": "pousado"
    },
    {
      "callsign": "TP4148",
      "airline": "TAP Air Portugal",
      "airport": "SBGR",
      "airport_name": "Sao Paulo / Guarulhos",
      "scheduled": "2026-05-16T20:10:00+00:00",
      "time_iso": "2026-05-16T19:58:00+00:00",
      "status": "pousado"
    },
    {
      "callsign": "CM3580",
      "airline": "Copa Airlines",
      "airport": "SBGR",
      "airport_name": "Sao Paulo / Guarulhos",
      "scheduled": "2026-05-16T20:10:00+00:00",
      "time_iso": "2026-05-16T19:58:00+00:00",
      "status": "pousado"
    },
    {
      "callsign": "AV4785",
      "airline": "avianca",
      "airport": "SBGR",
      "airport_name": "Sao Paulo / Guarulhos",
      "scheduled": "2026-05-16T20:10:00+00:00",
      "time_iso": "2026-05-16T19:58:00+00:00",
      "status": "pousado"
    },
    {
      "callsign": "AC9832",
      "airline": "Air Canada",
      "airport": "SBGR",
      "airport_name": "Sao Paulo / Guarulhos",
      "scheduled": "2026-05-16T20:10:00+00:00",
      "time_iso": "2026-05-16T19:58:00+00:00",
      "status": "pousado"
    },
    {
      "callsign": "QR5184",
      "airline": "Qatar Airways",
      "airport": "SBGR",
      "airport_name": "Sao Paulo / Guarulhos",
      "scheduled": "2026-05-16T18:55:00+00:00",
      "time_iso": "2026-05-16T18:56:00+00:00",
      "status": "em voo"
    },
    {
      "callsign": "G31180",
      "airline": "GOL",
      "airport": "SBGR",
      "airport_name": "Sao Paulo / Guarulhos",
      "scheduled": "2026-05-16T20:10:00+00:00",
      "time_iso": "2026-05-16T19:58:00+00:00",
      "status": "pousado"
    },
    {
      "callsign": "AD2406",
      "airline": "Azul",
      "airport": "SBKP",
      "airport_name": "Campinas / Viracopos",
      "scheduled": "2026-05-16T19:00:00+00:00",
      "time_iso": "2026-05-16T18:55:00+00:00",
      "status": "pousado"
    },
    {
      "callsign": "TP5992",
      "airline": "TAP Air Portugal",
      "airport": "SBGL",
      "airport_name": "Rio de Janeiro / Galeao",
      "scheduled": "2026-05-16T17:20:00+00:00",
      "time_iso": "2026-05-16T17:09:00+00:00",
      "status": "pousado"
    },
    {
      "callsign": "AD3059",
      "airline": "Azul",
      "airport": "SBGL",
      "airport_name": "Rio de Janeiro / Galeao",
      "scheduled": "2026-05-16T17:20:00+00:00",
      "time_iso": "2026-05-16T17:09:00+00:00",
      "status": "pousado"
    },
    {
      "callsign": "LA3204",
      "airline": "LATAM Airlines",
      "airport": "SBGR",
      "airport_name": "Sao Paulo / Guarulhos",
      "scheduled": "2026-05-16T18:55:00+00:00",
      "time_iso": "2026-05-16T18:56:00+00:00",
      "status": "em voo"
    },
    {
      "callsign": "LH4670",
      "airline": "Lufthansa",
      "airport": "SBGL",
      "airport_name": "Rio de Janeiro / Galeao",
      "scheduled": "2026-05-16T16:30:00+00:00",
      "time_iso": "2026-05-16T16:11:00+00:00",
      "status": "pousado"
    },
    {
      "callsign": "DL6147",
      "airline": "Delta Air Lines",
      "airport": "SBGL",
      "airport_name": "Rio de Janeiro / Galeao",
      "scheduled": "2026-05-16T16:30:00+00:00",
      "time_iso": "2026-05-16T16:11:00+00:00",
      "status": "pousado"
    },
    {
      "callsign": "BA7653",
      "airline": "British Airways",
      "airport": "SBGL",
      "airport_name": "Rio de Janeiro / Galeao",
      "scheduled": "2026-05-16T16:30:00+00:00",
      "time_iso": "2026-05-16T16:11:00+00:00",
      "status": "pousado"
    },
    {
      "callsign": "G31130",
      "airline": "GOL",
      "airport": "SBSP",
      "airport_name": "Sao Paulo / Congonhas",
      "scheduled": "2026-05-16T18:10:00+00:00",
      "time_iso": "2026-05-16T18:22:00+00:00",
      "status": "pousado"
    },
    {
      "callsign": "LA3481",
      "airline": "LATAM Airlines",
      "airport": "SBCT",
      "airport_name": "Curitiba",
      "scheduled": "2026-05-16T16:40:00+00:00",
      "time_iso": "2026-05-16T16:38:00+00:00",
      "status": "pousado"
    },
    {
      "callsign": "TP4005",
      "airline": "TAP Air Portugal",
      "airport": "SBGL",
      "airport_name": "Rio de Janeiro / Galeao",
      "scheduled": "2026-05-16T14:35:00+00:00",
      "time_iso": "2026-05-16T14:18:00+00:00",
      "status": "pousado"
    },
    {
      "callsign": "EK3687",
      "airline": "Emirates",
      "airport": "SBGL",
      "airport_name": "Rio de Janeiro / Galeao",
      "scheduled": "2026-05-17T02:15:00+00:00",
      "time_iso": "2026-05-17T01:52:00+00:00",
      "status": "pousado"
    },
    {
      "callsign": "AV2623",
      "airline": "avianca",
      "airport": "SBGL",
      "airport_name": "Rio de Janeiro / Galeao",
      "scheduled": "2026-05-16T14:35:00+00:00",
      "time_iso": "2026-05-16T14:18:00+00:00",
      "status": "pousado"
    },
    {
      "callsign": "AD3082",
      "airline": "Azul",
      "airport": "SBGL",
      "airport_name": "Rio de Janeiro / Galeao",
      "scheduled": "2026-05-16T14:35:00+00:00",
      "time_iso": "2026-05-16T14:18:00+00:00",
      "status": "pousado"
    },
    {
      "callsign": "AA7709",
      "airline": "American Airlines",
      "airport": "SBGL",
      "airport_name": "Rio de Janeiro / Galeao",
      "scheduled": "2026-05-16T14:35:00+00:00",
      "time_iso": "2026-05-16T14:18:00+00:00",
      "status": "pousado"
    },
    {
      "callsign": "G31390",
      "airline": "GOL",
      "airport": "SBGL",
      "airport_name": "Rio de Janeiro / Galeao",
      "scheduled": "2026-05-16T17:20:00+00:00",
      "time_iso": "2026-05-16T17:09:00+00:00",
      "status": "pousado"
    },
    {
      "callsign": "LA3290",
      "airline": "LATAM Airlines",
      "airport": "SBGL",
      "airport_name": "Rio de Janeiro / Galeao",
      "scheduled": "2026-05-16T16:30:00+00:00",
      "time_iso": "2026-05-16T16:11:00+00:00",
      "status": "pousado"
    },
    {
      "callsign": "TP6265",
      "airline": "TAP Air Portugal",
      "airport": "SBGR",
      "airport_name": "Sao Paulo / Guarulhos",
      "scheduled": "2026-05-16T13:50:00+00:00",
      "time_iso": "2026-05-16T13:40:00+00:00",
      "status": "pousado"
    },
    {
      "callsign": "QR7263",
      "airline": "Qatar Airways",
      "airport": "SBGR",
      "airport_name": "Sao Paulo / Guarulhos",
      "scheduled": "2026-05-16T13:50:00+00:00",
      "time_iso": "2026-05-16T13:40:00+00:00",
      "status": "pousado"
    },
    {
      "callsign": "IB6604",
      "airline": "Iberia",
      "airport": "SBGR",
      "airport_name": "Sao Paulo / Guarulhos",
      "scheduled": "2026-05-16T13:50:00+00:00",
      "time_iso": "2026-05-16T13:40:00+00:00",
      "status": "pousado"
    },
    {
      "callsign": "DL6269",
      "airline": "Delta Air Lines",
      "airport": "SBGR",
      "airport_name": "Sao Paulo / Guarulhos",
      "scheduled": "2026-05-16T13:50:00+00:00",
      "time_iso": "2026-05-16T13:40:00+00:00",
      "status": "pousado"
    },
    {
      "callsign": "BA7655",
      "airline": "British Airways",
      "airport": "SBGR",
      "airport_name": "Sao Paulo / Guarulhos",
      "scheduled": "2026-05-16T13:50:00+00:00",
      "time_iso": "2026-05-16T13:40:00+00:00",
      "status": "pousado"
    },
    {
      "callsign": "AM8526",
      "airline": "Aeromexico",
      "airport": "SBGR",
      "airport_name": "Sao Paulo / Guarulhos",
      "scheduled": "2026-05-16T13:50:00+00:00",
      "time_iso": "2026-05-16T13:40:00+00:00",
      "status": "pousado"
    },
    {
      "callsign": "AD2955",
      "airline": "Azul",
      "airport": "SBKP",
      "airport_name": "Campinas / Viracopos",
      "scheduled": "2026-05-16T14:40:00+00:00",
      "time_iso": "2026-05-16T14:48:00+00:00",
      "status": "em voo"
    },
    {
      "callsign": "G31862",
      "airline": "GOL",
      "airport": "SBGL",
      "airport_name": "Rio de Janeiro / Galeao",
      "scheduled": "2026-05-16T14:35:00+00:00",
      "time_iso": "2026-05-16T14:18:00+00:00",
      "status": "pousado"
    },
    {
      "callsign": "G31980",
      "airline": "GOL",
      "airport": "SBFZ",
      "airport_name": "Fortaleza",
      "scheduled": "2026-05-16T16:45:00+00:00",
      "time_iso": "2026-05-16T16:25:00+00:00",
      "status": "pousado"
    },
    {
      "callsign": "LA3202",
      "airline": "LATAM Airlines",
      "airport": "SBGR",
      "airport_name": "Sao Paulo / Guarulhos",
      "scheduled": "2026-05-16T13:50:00+00:00",
      "time_iso": "2026-05-16T13:40:00+00:00",
      "status": "pousado"
    }
  ],
  "departures": [
    {
      "callsign": "AD4726",
      "airline": "Azul",
      "airport": "SBKP",
      "airport_name": "Campinas / Viracopos",
      "scheduled": "2026-05-17T15:20:00+00:00",
      "time_iso": "2026-05-17T15:20:00+00:00",
      "status": "programado"
    },
    {
      "callsign": "G31123",
      "airline": "GOL",
      "airport": "SBSP",
      "airport_name": "Sao Paulo / Congonhas",
      "scheduled": "2026-05-17T14:55:00+00:00",
      "time_iso": "2026-05-17T14:55:00+00:00",
      "status": "programado"
    },
    {
      "callsign": "LA3879",
      "airline": "LATAM Airlines",
      "airport": "SBGR",
      "airport_name": "Sao Paulo / Guarulhos",
      "scheduled": "2026-05-17T14:50:00+00:00",
      "time_iso": "2026-05-17T14:50:00+00:00",
      "status": "programado"
    },
    {
      "callsign": "DL6175",
      "airline": "Delta Air Lines",
      "airport": "SBGR",
      "airport_name": "Sao Paulo / Guarulhos",
      "scheduled": "2026-05-17T14:50:00+00:00",
      "time_iso": "2026-05-17T14:50:00+00:00",
      "status": "programado"
    },
    {
      "callsign": "TK9554",
      "airline": "Turkish Airlines",
      "airport": "SBGR",
      "airport_name": "Sao Paulo / Guarulhos",
      "scheduled": "2026-05-17T14:50:00+00:00",
      "time_iso": "2026-05-17T14:50:00+00:00",
      "status": "programado"
    },
    {
      "callsign": "QR8417",
      "airline": "Qatar Airways",
      "airport": "SBGR",
      "airport_name": "Sao Paulo / Guarulhos",
      "scheduled": "2026-05-17T14:50:00+00:00",
      "time_iso": "2026-05-17T14:50:00+00:00",
      "status": "programado"
    },
    {
      "callsign": "LX9719",
      "airline": "Swiss",
      "airport": "SBGR",
      "airport_name": "Sao Paulo / Guarulhos",
      "scheduled": "2026-05-17T14:50:00+00:00",
      "time_iso": "2026-05-17T14:50:00+00:00",
      "status": "programado"
    },
    {
      "callsign": "LH4695",
      "airline": "Lufthansa",
      "airport": "SBGR",
      "airport_name": "Sao Paulo / Guarulhos",
      "scheduled": "2026-05-17T14:50:00+00:00",
      "time_iso": "2026-05-17T14:50:00+00:00",
      "status": "programado"
    },
    {
      "callsign": "DL6102",
      "airline": "Delta Air Lines",
      "airport": "SBGR",
      "airport_name": "Sao Paulo / Guarulhos",
      "scheduled": "2026-05-17T14:50:00+00:00",
      "time_iso": "2026-05-17T14:50:00+00:00",
      "status": "programado"
    },
    {
      "callsign": "G31945",
      "airline": "GOL",
      "airport": "SBGL",
      "airport_name": "Rio de Janeiro / Galeao",
      "scheduled": "2026-05-17T14:45:00+00:00",
      "time_iso": "2026-05-17T14:45:00+00:00",
      "status": "programado"
    },
    {
      "callsign": "AF1975",
      "airline": "Air France",
      "airport": "SBGL",
      "airport_name": "Rio de Janeiro / Galeao",
      "scheduled": "2026-05-17T14:45:00+00:00",
      "time_iso": "2026-05-17T14:45:00+00:00",
      "status": "programado"
    },
    {
      "callsign": "AA7676",
      "airline": "American Airlines",
      "airport": "SBGL",
      "airport_name": "Rio de Janeiro / Galeao",
      "scheduled": "2026-05-17T14:45:00+00:00",
      "time_iso": "2026-05-17T14:45:00+00:00",
      "status": "programado"
    },
    {
      "callsign": "TP5815",
      "airline": "TAP Air Portugal",
      "airport": "SBGL",
      "airport_name": "Rio de Janeiro / Galeao",
      "scheduled": "2026-05-17T14:45:00+00:00",
      "time_iso": "2026-05-17T14:45:00+00:00",
      "status": "programado"
    },
    {
      "callsign": "KL9463",
      "airline": "KLM",
      "airport": "SBGL",
      "airport_name": "Rio de Janeiro / Galeao",
      "scheduled": "2026-05-17T14:45:00+00:00",
      "time_iso": "2026-05-17T14:45:00+00:00",
      "status": "programado"
    },
    {
      "callsign": "AD3133",
      "airline": "Azul",
      "airport": "SBGL",
      "airport_name": "Rio de Janeiro / Galeao",
      "scheduled": "2026-05-17T14:45:00+00:00",
      "time_iso": "2026-05-17T14:45:00+00:00",
      "status": "programado"
    },
    {
      "callsign": "AD5022",
      "airline": "Azul",
      "airport": "SBSP",
      "airport_name": "Sao Paulo / Congonhas",
      "scheduled": "2026-05-17T14:10:00+00:00",
      "time_iso": "2026-05-17T14:10:00+00:00",
      "status": "programado"
    },
    {
      "callsign": "LA3482",
      "airline": "LATAM Airlines",
      "airport": "SBCT",
      "airport_name": "Curitiba",
      "scheduled": "2026-05-17T13:35:00+00:00",
      "time_iso": "2026-05-17T13:35:00+00:00",
      "status": "programado"
    },
    {
      "callsign": "AD4130",
      "airline": "Azul",
      "airport": "SBCT",
      "airport_name": "Curitiba",
      "scheduled": "2026-05-17T12:45:00+00:00",
      "time_iso": "2026-05-17T12:45:00+00:00",
      "status": "programado"
    },
    {
      "callsign": "LA3685",
      "airline": "LATAM Airlines",
      "airport": "SBGL",
      "airport_name": "Rio de Janeiro / Galeao",
      "scheduled": "2026-05-17T11:35:00+00:00",
      "time_iso": "2026-05-17T11:35:00+00:00",
      "status": "programado"
    },
    {
      "callsign": "LH4671",
      "airline": "Lufthansa",
      "airport": "SBGL",
      "airport_name": "Rio de Janeiro / Galeao",
      "scheduled": "2026-05-17T11:35:00+00:00",
      "time_iso": "2026-05-17T11:35:00+00:00",
      "status": "programado"
    },
    {
      "callsign": "IB6495",
      "airline": "Iberia",
      "airport": "SBGL",
      "airport_name": "Rio de Janeiro / Galeao",
      "scheduled": "2026-05-17T11:35:00+00:00",
      "time_iso": "2026-05-17T11:35:00+00:00",
      "status": "programado"
    },
    {
      "callsign": "BA7652",
      "airline": "British Airways",
      "airport": "SBGL",
      "airport_name": "Rio de Janeiro / Galeao",
      "scheduled": "2026-05-17T11:35:00+00:00",
      "time_iso": "2026-05-17T11:35:00+00:00",
      "status": "programado"
    },
    {
      "callsign": "G31179",
      "airline": "GOL",
      "airport": "SBGR",
      "airport_name": "Sao Paulo / Guarulhos",
      "scheduled": "2026-05-17T11:15:00+00:00",
      "time_iso": "2026-05-17T11:15:00+00:00",
      "status": "programado"
    },
    {
      "callsign": "SA2364",
      "airline": "South African Airways",
      "airport": "SBGR",
      "airport_name": "Sao Paulo / Guarulhos",
      "scheduled": "2026-05-17T11:15:00+00:00",
      "time_iso": "2026-05-17T11:15:00+00:00",
      "status": "programado"
    },
    {
      "callsign": "AT9084",
      "airline": "Royal Air Maroc",
      "airport": "SBGR",
      "airport_name": "Sao Paulo / Guarulhos",
      "scheduled": "2026-05-17T11:15:00+00:00",
      "time_iso": "2026-05-17T11:15:00+00:00",
      "status": "programado"
    },
    {
      "callsign": "TP5802",
      "airline": "TAP Air Portugal",
      "airport": "SBGR",
      "airport_name": "Sao Paulo / Guarulhos",
      "scheduled": "2026-05-17T11:15:00+00:00",
      "time_iso": "2026-05-17T11:15:00+00:00",
      "status": "programado"
    },
    {
      "callsign": "KL9317",
      "airline": "KLM",
      "airport": "SBGR",
      "airport_name": "Sao Paulo / Guarulhos",
      "scheduled": "2026-05-17T11:15:00+00:00",
      "time_iso": "2026-05-17T11:15:00+00:00",
      "status": "programado"
    },
    {
      "callsign": "ET4203",
      "airline": "Ethiopian Airlines",
      "airport": "SBGR",
      "airport_name": "Sao Paulo / Guarulhos",
      "scheduled": "2026-05-17T11:15:00+00:00",
      "time_iso": "2026-05-17T11:15:00+00:00",
      "status": "programado"
    },
    {
      "callsign": "EK3628",
      "airline": "Emirates",
      "airport": "SBGR",
      "airport_name": "Sao Paulo / Guarulhos",
      "scheduled": "2026-05-17T11:15:00+00:00",
      "time_iso": "2026-05-17T11:15:00+00:00",
      "status": "programado"
    },
    {
      "callsign": "DT6671",
      "airline": "TAAG Angola Airlines",
      "airport": "SBGR",
      "airport_name": "Sao Paulo / Guarulhos",
      "scheduled": "2026-05-17T11:15:00+00:00",
      "time_iso": "2026-05-17T11:15:00+00:00",
      "status": "programado"
    },
    {
      "callsign": "AV4702",
      "airline": "avianca",
      "airport": "SBGR",
      "airport_name": "Sao Paulo / Guarulhos",
      "scheduled": "2026-05-17T11:15:00+00:00",
      "time_iso": "2026-05-17T11:15:00+00:00",
      "status": "programado"
    },
    {
      "callsign": "AF2048",
      "airline": "Air France",
      "airport": "SBGR",
      "airport_name": "Sao Paulo / Guarulhos",
      "scheduled": "2026-05-17T11:15:00+00:00",
      "time_iso": "2026-05-17T11:15:00+00:00",
      "status": "programado"
    },
    {
      "callsign": "AC9821",
      "airline": "Air Canada",
      "airport": "SBGR",
      "airport_name": "Sao Paulo / Guarulhos",
      "scheduled": "2026-05-17T11:15:00+00:00",
      "time_iso": "2026-05-17T11:15:00+00:00",
      "status": "programado"
    },
    {
      "callsign": "G31861",
      "airline": "GOL",
      "airport": "SBGL",
      "airport_name": "Rio de Janeiro / Galeao",
      "scheduled": "2026-05-17T10:15:00+00:00",
      "time_iso": "2026-05-17T10:15:00+00:00",
      "status": "em voo"
    },
    {
      "callsign": "TP4224",
      "airline": "TAP Air Portugal",
      "airport": "SBGL",
      "airport_name": "Rio de Janeiro / Galeao",
      "scheduled": "2026-05-17T10:15:00+00:00",
      "time_iso": "2026-05-17T10:15:00+00:00",
      "status": "em voo"
    },
    {
      "callsign": "KL9379",
      "airline": "KLM",
      "airport": "SBGL",
      "airport_name": "Rio de Janeiro / Galeao",
      "scheduled": "2026-05-17T10:15:00+00:00",
      "time_iso": "2026-05-17T10:15:00+00:00",
      "status": "em voo"
    },
    {
      "callsign": "TP4103",
      "airline": "TAP Air Portugal",
      "airport": "SBGL",
      "airport_name": "Rio de Janeiro / Galeao",
      "scheduled": "2026-05-17T10:15:00+00:00",
      "time_iso": "2026-05-17T10:15:00+00:00",
      "status": "em voo"
    },
    {
      "callsign": "AV2640",
      "airline": "avianca",
      "airport": "SBGL",
      "airport_name": "Rio de Janeiro / Galeao",
      "scheduled": "2026-05-17T10:15:00+00:00",
      "time_iso": "2026-05-17T10:15:00+00:00",
      "status": "em voo"
    },
    {
      "callsign": "AD3089",
      "airline": "Azul",
      "airport": "SBGL",
      "airport_name": "Rio de Janeiro / Galeao",
      "scheduled": "2026-05-17T10:15:00+00:00",
      "time_iso": "2026-05-17T10:15:00+00:00",
      "status": "em voo"
    },
    {
      "callsign": "LA3201",
      "airline": "LATAM Airlines",
      "airport": "SBGR",
      "airport_name": "Sao Paulo / Guarulhos",
      "scheduled": "2026-05-17T10:05:00+00:00",
      "time_iso": "2026-05-17T10:05:00+00:00",
      "status": "em voo"
    },
    {
      "callsign": "TP6266",
      "airline": "TAP Air Portugal",
      "airport": "SBGR",
      "airport_name": "Sao Paulo / Guarulhos",
      "scheduled": "2026-05-17T10:05:00+00:00",
      "time_iso": "2026-05-17T10:05:00+00:00",
      "status": "em voo"
    },
    {
      "callsign": "QR5256",
      "airline": "Qatar Airways",
      "airport": "SBGR",
      "airport_name": "Sao Paulo / Guarulhos",
      "scheduled": "2026-05-17T10:05:00+00:00",
      "time_iso": "2026-05-17T10:05:00+00:00",
      "status": "em voo"
    },
    {
      "callsign": "IB6519",
      "airline": "Iberia",
      "airport": "SBGR",
      "airport_name": "Sao Paulo / Guarulhos",
      "scheduled": "2026-05-17T10:05:00+00:00",
      "time_iso": "2026-05-17T10:05:00+00:00",
      "status": "em voo"
    },
    {
      "callsign": "BA7654",
      "airline": "British Airways",
      "airport": "SBGR",
      "airport_name": "Sao Paulo / Guarulhos",
      "scheduled": "2026-05-17T10:05:00+00:00",
      "time_iso": "2026-05-17T10:05:00+00:00",
      "status": "em voo"
    },
    {
      "callsign": "JA787",
      "airline": "JetSMART",
      "airport": "SCEL",
      "airport_name": "SCEL",
      "scheduled": "2026-05-17T09:05:00+00:00",
      "time_iso": "2026-05-17T09:23:00+00:00",
      "status": "em voo"
    },
    {
      "callsign": "AD6075",
      "airline": "Azul",
      "airport": "SBSP",
      "airport_name": "Sao Paulo / Congonhas",
      "scheduled": "2026-05-17T09:00:00+00:00",
      "time_iso": "2026-05-17T09:08:00+00:00",
      "status": "em voo"
    },
    {
      "callsign": "G31133",
      "airline": "GOL",
      "airport": "SBSP",
      "airport_name": "Sao Paulo / Congonhas",
      "scheduled": "2026-05-17T07:10:00+00:00",
      "time_iso": "2026-05-17T07:10:00+00:00",
      "status": "em voo"
    },
    {
      "callsign": "LA3385",
      "airline": "LATAM Airlines",
      "airport": "SBSP",
      "airport_name": "Sao Paulo / Congonhas",
      "scheduled": "2026-05-17T08:00:00+00:00",
      "time_iso": "2026-05-17T08:14:00+00:00",
      "status": "em voo"
    },
    {
      "callsign": "G31183",
      "airline": "GOL",
      "airport": "SBGR",
      "airport_name": "Sao Paulo / Guarulhos",
      "scheduled": "2026-05-17T06:10:00+00:00",
      "time_iso": "2026-05-17T06:10:00+00:00",
      "status": "em voo"
    },
    {
      "callsign": "SA2363",
      "airline": "South African Airways",
      "airport": "SBGR",
      "airport_name": "Sao Paulo / Guarulhos",
      "scheduled": "2026-05-17T06:10:00+00:00",
      "time_iso": "2026-05-17T06:10:00+00:00",
      "status": "em voo"
    },
    {
      "callsign": "UX2624",
      "airline": "Air Europa",
      "airport": "SBGR",
      "airport_name": "Sao Paulo / Guarulhos",
      "scheduled": "2026-05-17T06:10:00+00:00",
      "time_iso": "2026-05-17T06:10:00+00:00",
      "status": "em voo"
    },
    {
      "callsign": "TP4181",
      "airline": "TAP Air Portugal",
      "airport": "SBGR",
      "airport_name": "Sao Paulo / Guarulhos",
      "scheduled": "2026-05-17T06:10:00+00:00",
      "time_iso": "2026-05-17T06:10:00+00:00",
      "status": "em voo"
    },
    {
      "callsign": "KL9319",
      "airline": "KLM",
      "airport": "SBGR",
      "airport_name": "Sao Paulo / Guarulhos",
      "scheduled": "2026-05-17T06:10:00+00:00",
      "time_iso": "2026-05-17T06:10:00+00:00",
      "status": "em voo"
    },
    {
      "callsign": "DT6673",
      "airline": "TAAG Angola Airlines",
      "airport": "SBGR",
      "airport_name": "Sao Paulo / Guarulhos",
      "scheduled": "2026-05-17T06:10:00+00:00",
      "time_iso": "2026-05-17T06:10:00+00:00",
      "status": "em voo"
    },
    {
      "callsign": "CM3643",
      "airline": "Copa Airlines",
      "airport": "SBGR",
      "airport_name": "Sao Paulo / Guarulhos",
      "scheduled": "2026-05-17T06:10:00+00:00",
      "time_iso": "2026-05-17T06:10:00+00:00",
      "status": "em voo"
    },
    {
      "callsign": "AM8098",
      "airline": "Aeromexico",
      "airport": "SBGR",
      "airport_name": "Sao Paulo / Guarulhos",
      "scheduled": "2026-05-17T06:10:00+00:00",
      "time_iso": "2026-05-17T06:10:00+00:00",
      "status": "em voo"
    },
    {
      "callsign": "AF2049",
      "airline": "Air France",
      "airport": "SBGR",
      "airport_name": "Sao Paulo / Guarulhos",
      "scheduled": "2026-05-17T06:10:00+00:00",
      "time_iso": "2026-05-17T06:10:00+00:00",
      "status": "em voo"
    },
    {
      "callsign": "G31869",
      "airline": "GOL",
      "airport": "SBGL",
      "airport_name": "Rio de Janeiro / Galeao",
      "scheduled": "2026-05-17T05:40:00+00:00",
      "time_iso": "2026-05-17T05:40:00+00:00",
      "status": "em voo"
    },
    {
      "callsign": "TP4057",
      "airline": "TAP Air Portugal",
      "airport": "SBGL",
      "airport_name": "Rio de Janeiro / Galeao",
      "scheduled": "2026-05-17T05:40:00+00:00",
      "time_iso": "2026-05-17T05:40:00+00:00",
      "status": "em voo"
    },
    {
      "callsign": "EK3690",
      "airline": "Emirates",
      "airport": "SBGL",
      "airport_name": "Rio de Janeiro / Galeao",
      "scheduled": "2026-05-17T05:40:00+00:00",
      "time_iso": "2026-05-17T05:40:00+00:00",
      "status": "em voo"
    },
    {
      "callsign": "AD3090",
      "airline": "Azul",
      "airport": "SBGL",
      "airport_name": "Rio de Janeiro / Galeao",
      "scheduled": "2026-05-17T05:40:00+00:00",
      "time_iso": "2026-05-17T05:40:00+00:00",
      "status": "em voo"
    },
    {
      "callsign": "LA3397",
      "airline": "LATAM Airlines",
      "airport": "SBGR",
      "airport_name": "Sao Paulo / Guarulhos",
      "scheduled": "2026-05-17T04:45:00+00:00",
      "time_iso": "2026-05-17T04:45:00+00:00",
      "status": "em voo"
    },
    {
      "callsign": "CA7124",
      "airline": "Air China",
      "airport": "SBGR",
      "airport_name": "Sao Paulo / Guarulhos",
      "scheduled": "2026-05-17T04:45:00+00:00",
      "time_iso": "2026-05-17T04:45:00+00:00",
      "status": "em voo"
    },
    {
      "callsign": "IB6605",
      "airline": "Iberia",
      "airport": "SBGR",
      "airport_name": "Sao Paulo / Guarulhos",
      "scheduled": "2026-05-17T04:45:00+00:00",
      "time_iso": "2026-05-17T04:45:00+00:00",
      "status": "em voo"
    },
    {
      "callsign": "DL6217",
      "airline": "Delta Air Lines",
      "airport": "SBGR",
      "airport_name": "Sao Paulo / Guarulhos",
      "scheduled": "2026-05-17T04:45:00+00:00",
      "time_iso": "2026-05-17T04:45:00+00:00",
      "status": "em voo"
    },
    {
      "callsign": "AM8527",
      "airline": "Aeromexico",
      "airport": "SBGR",
      "airport_name": "Sao Paulo / Guarulhos",
      "scheduled": "2026-05-17T04:45:00+00:00",
      "time_iso": "2026-05-17T04:45:00+00:00",
      "status": "em voo"
    },
    {
      "callsign": "AD4865",
      "airline": "Azul",
      "airport": "SBKP",
      "airport_name": "Campinas / Viracopos",
      "scheduled": "2026-05-16T19:50:00+00:00",
      "time_iso": "2026-05-16T20:05:00+00:00",
      "status": "pousado"
    },
    {
      "callsign": "LA3205",
      "airline": "LATAM Airlines",
      "airport": "SBGR",
      "airport_name": "Sao Paulo / Guarulhos",
      "scheduled": "2026-05-16T19:40:00+00:00",
      "time_iso": "2026-05-16T19:52:00+00:00",
      "status": "pousado"
    },
    {
      "callsign": "DL6215",
      "airline": "Delta Air Lines",
      "airport": "SBGR",
      "airport_name": "Sao Paulo / Guarulhos",
      "scheduled": "2026-05-16T19:40:00+00:00",
      "time_iso": "2026-05-16T19:52:00+00:00",
      "status": "em voo"
    },
    {
      "callsign": "TK9036",
      "airline": "Turkish Airlines",
      "airport": "SBGR",
      "airport_name": "Sao Paulo / Guarulhos",
      "scheduled": "2026-05-16T19:40:00+00:00",
      "time_iso": "2026-05-16T19:52:00+00:00",
      "status": "pousado"
    },
    {
      "callsign": "QR5287",
      "airline": "Qatar Airways",
      "airport": "SBGR",
      "airport_name": "Sao Paulo / Guarulhos",
      "scheduled": "2026-05-16T19:40:00+00:00",
      "time_iso": "2026-05-16T19:52:00+00:00",
      "status": "pousado"
    },
    {
      "callsign": "JL5549",
      "airline": "Japan Airlines",
      "airport": "SBGR",
      "airport_name": "Sao Paulo / Guarulhos",
      "scheduled": "2026-05-16T19:40:00+00:00",
      "time_iso": "2026-05-16T19:52:00+00:00",
      "status": "pousado"
    },
    {
      "callsign": "DL6218",
      "airline": "Delta Air Lines",
      "airport": "SBGR",
      "airport_name": "Sao Paulo / Guarulhos",
      "scheduled": "2026-05-16T19:40:00+00:00",
      "time_iso": "2026-05-16T19:52:00+00:00",
      "status": "pousado"
    },
    {
      "callsign": "G31391",
      "airline": "GOL",
      "airport": "SBGL",
      "airport_name": "Rio de Janeiro / Galeao",
      "scheduled": "2026-05-16T18:05:00+00:00",
      "time_iso": "2026-05-16T18:09:00+00:00",
      "status": "pousado"
    },
    {
      "callsign": "TP4226",
      "airline": "TAP Air Portugal",
      "airport": "SBGL",
      "airport_name": "Rio de Janeiro / Galeao",
      "scheduled": "2026-05-16T18:05:00+00:00",
      "time_iso": "2026-05-16T18:09:00+00:00",
      "status": "pousado"
    },
    {
      "callsign": "KL9379",
      "airline": "KLM",
      "airport": "SBGL",
      "airport_name": "Rio de Janeiro / Galeao",
      "scheduled": "2026-05-16T18:05:00+00:00",
      "time_iso": "2026-05-16T18:09:00+00:00",
      "status": "pousado"
    },
    {
      "callsign": "AV2604",
      "airline": "avianca",
      "airport": "SBGL",
      "airport_name": "Rio de Janeiro / Galeao",
      "scheduled": "2026-05-16T18:05:00+00:00",
      "time_iso": "2026-05-16T18:09:00+00:00",
      "status": "pousado"
    },
    {
      "callsign": "AF2040",
      "airline": "Air France",
      "airport": "SBGL",
      "airport_name": "Rio de Janeiro / Galeao",
      "scheduled": "2026-05-16T18:05:00+00:00",
      "time_iso": "2026-05-16T18:09:00+00:00",
      "status": "pousado"
    },
    {
      "callsign": "AD3088",
      "airline": "Azul",
      "airport": "SBGL",
      "airport_name": "Rio de Janeiro / Galeao",
      "scheduled": "2026-05-16T18:05:00+00:00",
      "time_iso": "2026-05-16T18:09:00+00:00",
      "status": "pousado"
    },
    {
      "callsign": "AA7676",
      "airline": "American Airlines",
      "airport": "SBGL",
      "airport_name": "Rio de Janeiro / Galeao",
      "scheduled": "2026-05-16T18:05:00+00:00",
      "time_iso": "2026-05-16T18:09:00+00:00",
      "status": "pousado"
    },
    {
      "callsign": "LA3109",
      "airline": "LATAM Airlines",
      "airport": "SBSP",
      "airport_name": "Sao Paulo / Congonhas",
      "scheduled": "2026-05-16T17:35:00+00:00",
      "time_iso": "2026-05-16T17:43:00+00:00",
      "status": "pousado"
    },
    {
      "callsign": "G31981",
      "airline": "GOL",
      "airport": "SBFZ",
      "airport_name": "Fortaleza",
      "scheduled": "2026-05-16T17:25:00+00:00",
      "time_iso": "2026-05-16T17:31:00+00:00",
      "status": "pousado"
    },
    {
      "callsign": "LA3461",
      "airline": "LATAM Airlines",
      "airport": "SBBR",
      "airport_name": "Brasilia",
      "scheduled": "2026-05-16T17:15:00+00:00",
      "time_iso": "2026-05-16T17:24:00+00:00",
      "status": "pousado"
    },
    {
      "callsign": "AD2407",
      "airline": "Azul",
      "airport": "SBKP",
      "airport_name": "Campinas / Viracopos",
      "scheduled": "2026-05-16T15:20:00+00:00",
      "time_iso": "2026-05-16T15:37:00+00:00",
      "status": "pousado"
    },
    {
      "callsign": "G31863",
      "airline": "GOL",
      "airport": "SBGL",
      "airport_name": "Rio de Janeiro / Galeao",
      "scheduled": "2026-05-16T15:15:00+00:00",
      "time_iso": "2026-05-16T15:28:00+00:00",
      "status": "pousado"
    },
    {
      "callsign": "TP4009",
      "airline": "TAP Air Portugal",
      "airport": "SBGL",
      "airport_name": "Rio de Janeiro / Galeao",
      "scheduled": "2026-05-16T15:15:00+00:00",
      "time_iso": "2026-05-16T15:28:00+00:00",
      "status": "pousado"
    },
    {
      "callsign": "KL9463",
      "airline": "KLM",
      "airport": "SBGL",
      "airport_name": "Rio de Janeiro / Galeao",
      "scheduled": "2026-05-16T15:15:00+00:00",
      "time_iso": "2026-05-16T15:28:00+00:00",
      "status": "pousado"
    },
    {
      "callsign": "EK3688",
      "airline": "Emirates",
      "airport": "SBGL",
      "airport_name": "Rio de Janeiro / Galeao",
      "scheduled": "2026-05-16T15:15:00+00:00",
      "time_iso": "2026-05-16T15:28:00+00:00",
      "status": "pousado"
    },
    {
      "callsign": "AD3002",
      "airline": "Azul",
      "airport": "SBGL",
      "airport_name": "Rio de Janeiro / Galeao",
      "scheduled": "2026-05-16T15:15:00+00:00",
      "time_iso": "2026-05-16T15:28:00+00:00",
      "status": "pousado"
    },
    {
      "callsign": "LA3879",
      "airline": "LATAM Airlines",
      "airport": "SBGR",
      "airport_name": "Sao Paulo / Guarulhos",
      "scheduled": "2026-05-16T14:40:00+00:00",
      "time_iso": "2026-05-16T14:52:00+00:00",
      "status": "pousado"
    },
    {
      "callsign": "DL6102",
      "airline": "Delta Air Lines",
      "airport": "SBGR",
      "airport_name": "Sao Paulo / Guarulhos",
      "scheduled": "2026-05-16T14:40:00+00:00",
      "time_iso": "2026-05-16T14:40:00+00:00",
      "status": "em voo"
    },
    {
      "callsign": "TK9554",
      "airline": "Turkish Airlines",
      "airport": "SBGR",
      "airport_name": "Sao Paulo / Guarulhos",
      "scheduled": "2026-05-16T14:40:00+00:00",
      "time_iso": "2026-05-16T14:52:00+00:00",
      "status": "pousado"
    },
    {
      "callsign": "QR8417",
      "airline": "Qatar Airways",
      "airport": "SBGR",
      "airport_name": "Sao Paulo / Guarulhos",
      "scheduled": "2026-05-16T14:40:00+00:00",
      "time_iso": "2026-05-16T14:52:00+00:00",
      "status": "pousado"
    },
    {
      "callsign": "LX9719",
      "airline": "Swiss",
      "airport": "SBGR",
      "airport_name": "Sao Paulo / Guarulhos",
      "scheduled": "2026-05-16T14:40:00+00:00",
      "time_iso": "2026-05-16T14:52:00+00:00",
      "status": "pousado"
    },
    {
      "callsign": "LH4695",
      "airline": "Lufthansa",
      "airport": "SBGR",
      "airport_name": "Sao Paulo / Guarulhos",
      "scheduled": "2026-05-16T14:40:00+00:00",
      "time_iso": "2026-05-16T14:52:00+00:00",
      "status": "pousado"
    },
    {
      "callsign": "AD5022",
      "airline": "Azul",
      "airport": "SBSP",
      "airport_name": "Sao Paulo / Congonhas",
      "scheduled": "2026-05-16T14:35:00+00:00",
      "time_iso": "2026-05-16T14:36:00+00:00",
      "status": "pousado"
    },
    {
      "callsign": "G31123",
      "airline": "GOL",
      "airport": "SBSP",
      "airport_name": "Sao Paulo / Congonhas",
      "scheduled": "2026-05-16T14:20:00+00:00",
      "time_iso": "2026-05-16T14:23:00+00:00",
      "status": "pousado"
    },
    {
      "callsign": "LA3482",
      "airline": "LATAM Airlines",
      "airport": "SBCT",
      "airport_name": "Curitiba",
      "scheduled": "2026-05-16T13:35:00+00:00",
      "time_iso": "2026-05-16T13:53:00+00:00",
      "status": "pousado"
    },
    {
      "callsign": "AD4130",
      "airline": "Azul",
      "airport": "SBCT",
      "airport_name": "Curitiba",
      "scheduled": "2026-05-16T13:00:00+00:00",
      "time_iso": "2026-05-16T13:08:00+00:00",
      "status": "pousado"
    },
    {
      "callsign": "LA3685",
      "airline": "LATAM Airlines",
      "airport": "SBGL",
      "airport_name": "Rio de Janeiro / Galeao",
      "scheduled": "2026-05-16T11:35:00+00:00",
      "time_iso": "2026-05-16T11:32:00+00:00",
      "status": "pousado"
    }
  ]
}